[{"__type__":"cc.SpriteFrame","content":{"name":"Num25","texture":"8522yZUJJFo6jAmPsYGqMn","rect":[2,2,845,592],"offset":[0,0],"originalSize":[845,592],"capInsets":[0,0,0,0]}},{"__type__":"cc.SpriteFrame","content":{"name":"Num8","texture":"8522yZUJJFo6jAmPsYGqMn","rect":[783,596,248,85],"offset":[0,0],"originalSize":[248,85],"rotated":1,"capInsets":[0,0,0,0]}},{"__type__":"cc.SpriteFrame","content":{"name":"Num16","texture":"8522yZUJJFo6jAmPsYGqMn","rect":[522,772,257,86],"offset":[0,0],"originalSize":[257,86],"capInsets":[0,0,0,0]}},{"__type__":"cc.SpriteFrame","content":{"name":"Num13","texture":"8522yZUJJFo6jAmPsYGqMn","rect":[524,596,257,87],"offset":[0,0],"originalSize":[257,87],"capInsets":[0,0,0,0]}},{"__type__":"cc.SpriteFrame","content":{"name":"Num17","texture":"8522yZUJJFo6jAmPsYGqMn","rect":[870,524,248,86],"offset":[0,0],"originalSize":[248,86],"rotated":1,"capInsets":[0,0,0,0]}},{"__type__":"cc.SpriteFrame","content":{"name":"Num18","texture":"8522yZUJJFo6jAmPsYGqMn","rect":[2,774,259,86],"offset":[0,0],"originalSize":[259,86],"capInsets":[0,0,0,0]}},{"__type__":"cc.SpriteFrame","content":{"name":"Num20","texture":"8522yZUJJFo6jAmPsYGqMn","rect":[870,774,248,85],"offset":[0,0],"originalSize":[248,85],"rotated":1,"capInsets":[0,0,0,0]}},{"__type__":"cc.SpriteFrame","content":{"name":"Num11","texture":"8522yZUJJFo6jAmPsYGqMn","rect":[2,862,257,87],"offset":[0,0],"originalSize":[257,87],"capInsets":[0,0,0,0]}},{"__type__":"cc.SpriteFrame","content":{"name":"Num12","texture":"8522yZUJJFo6jAmPsYGqMn","rect":[263,596,259,87],"offset":[0,0],"originalSize":[259,87],"capInsets":[0,0,0,0]}},{"__type__":"cc.SpriteFrame","content":{"name":"Num14","texture":"8522yZUJJFo6jAmPsYGqMn","rect":[513,1037,248,87],"offset":[0,0],"originalSize":[248,87],"capInsets":[0,0,0,0]}},{"__type__":"cc.SpriteFrame","content":{"name":"Num23","texture":"8522yZUJJFo6jAmPsYGqMn","rect":[263,685,257,87],"offset":[0,0],"originalSize":[257,87],"capInsets":[0,0,0,0]}},{"__type__":"cc.SpriteFrame","content":{"name":"Num1","texture":"8522yZUJJFo6jAmPsYGqMn","rect":[2,951,257,87],"offset":[0,0],"originalSize":[257,87],"capInsets":[0,0,0,0]}},{"__type__":"cc.SpriteFrame","content":{"name":"Num10","texture":"8522yZUJJFo6jAmPsYGqMn","rect":[781,846,248,87],"offset":[0,0],"originalSize":[248,87],"rotated":1,"capInsets":[0,0,0,0]}},{"__type__":"cc.SpriteFrame","content":{"name":"Num2","texture":"8522yZUJJFo6jAmPsYGqMn","rect":[522,860,248,87],"offset":[0,0],"originalSize":[248,87],"capInsets":[0,0,0,0]}},{"__type__":"cc.SpriteFrame","content":{"name":"Num5","texture":"8522yZUJJFo6jAmPsYGqMn","rect":[520,949,248,86],"offset":[0,0],"originalSize":[248,86],"capInsets":[0,0,0,0]}},{"__type__":"cc.SpriteFrame","content":{"name":"Num21","texture":"8522yZUJJFo6jAmPsYGqMn","rect":[2,1040,259,85],"offset":[0,0],"originalSize":[259,85],"capInsets":[0,0,0,0]}},{"__type__":"cc.SpriteFrame","content":{"name":"Num9","texture":"8522yZUJJFo6jAmPsYGqMn","rect":[522,685,259,85],"offset":[0,0],"originalSize":[259,85],"capInsets":[0,0,0,0]}},{"__type__":"cc.SpriteFrame","content":{"name":"Num22","texture":"8522yZUJJFo6jAmPsYGqMn","rect":[263,1036,248,87],"offset":[0,0],"originalSize":[248,87],"capInsets":[0,0,0,0]}},{"__type__":"cc.SpriteFrame","content":{"name":"Num15","texture":"8522yZUJJFo6jAmPsYGqMn","rect":[2,685,259,87],"offset":[0,0],"originalSize":[259,87],"capInsets":[0,0,0,0]}},{"__type__":"cc.SpriteFrame","content":{"name":"Num4","texture":"8522yZUJJFo6jAmPsYGqMn","rect":[263,774,257,86],"offset":[0,0],"originalSize":[257,86],"capInsets":[0,0,0,0]}},{"__type__":"cc.SpriteFrame","content":{"name":"Num3","texture":"8522yZUJJFo6jAmPsYGqMn","rect":[2,596,259,87],"offset":[0,0],"originalSize":[259,87],"capInsets":[0,0,0,0]}},{"__type__":"cc.SpriteFrame","content":{"name":"Num6","texture":"8522yZUJJFo6jAmPsYGqMn","rect":[849,263,259,86],"offset":[0,0],"originalSize":[259,86],"rotated":1,"capInsets":[0,0,0,0]}},{"__type__":"cc.SpriteFrame","content":{"name":"Num19","texture":"8522yZUJJFo6jAmPsYGqMn","rect":[261,949,257,85],"offset":[0,0],"originalSize":[257,85],"capInsets":[0,0,0,0]}},{"__type__":"cc.SpriteAtlas","_name":"JoinRoom.plist","_spriteFrames":{"Num1":{"__uuid__":"9aAV/085tBpbwf//ctr822"},"Num10":{"__uuid__":"a8VugHwTJOkb2huVoFkykb"},"Num11":{"__uuid__":"59eIQ5XQxBJIQrRNA+IfG9"},"Num12":{"__uuid__":"61tMwjEtVF7qMCsV1UrK9M"},"Num13":{"__uuid__":"27Kx5YBGlDpJetEsC6KKp3"},"Num14":{"__uuid__":"67pKIe6+dPFpk9qPnCVJ59"},"Num15":{"__uuid__":"c9uGQeMGNGNLJCy1imoSFe"},"Num16":{"__uuid__":"1biFPyKcRMHqBNOXbU/KMO"},"Num17":{"__uuid__":"4d6Du3tw1EY5kdFxNw0VXs"},"Num18":{"__uuid__":"56PWIs/FtHM63+nDw3BrCc"},"Num19":{"__uuid__":"d9nUsr5hJI7qKd9l1RP+w9"},"Num2":{"__uuid__":"aaM94Dm1VFnbWwjnxvsgsA"},"Num20":{"__uuid__":"58P5mL2oJKX6snEhCfSV+m"},"Num21":{"__uuid__":"acZuaQhudK7pNo+p4CZD4L"},"Num22":{"__uuid__":"bbbGrQXjZHPaQfNw3838zl"},"Num23":{"__uuid__":"6ebMtvsw5Ms5+R7W1ZABQQ"},"Num24":{"__uuid__":"ffTm2CJkROS5/jLtEOxEKf"},"Num25":{"__uuid__":"03pmYK7nZIloZzD5ueZaHA"},"Num3":{"__uuid__":"cfdjnVP1RBYJTmASmNNf0C"},"Num4":{"__uuid__":"cbEM/EAIhLxY87oq8A+4ix"},"Num5":{"__uuid__":"aaUu8hdalFrJclr79HPfC3"},"Num6":{"__uuid__":"d5EZ1nUiREA4EwWhtQEoKA"},"Num7":{"__uuid__":"fb1PWFS59IP4KrAghbkrOO"},"Num8":{"__uuid__":"0dUw3ifGlAe6geWPiqNekq"},"Num9":{"__uuid__":"b1hRiGZlRI+LvaIvdi0+Oz"}}},{"__type__":"cc.SpriteFrame","content":{"name":"Num7","texture":"8522yZUJJFo6jAmPsYGqMn","rect":[261,862,257,85],"offset":[0,0],"originalSize":[257,85],"capInsets":[0,0,0,0]}},{"__type__":"cc.SpriteFrame","content":{"name":"Num24","texture":"8522yZUJJFo6jAmPsYGqMn","rect":[849,2,259,87],"offset":[0,0],"originalSize":[259,87],"rotated":1,"capInsets":[0,0,0,0]}}]